src/__init__.py
src/__main__.py
src/client.py
src/config.py
src/scanner.py
src/apply/__init__.py
src/apply/create_project.py
src/apply/create_self_check.py
src/apply/execute_command.py
src/commands/__init__.py
src/commands/apply.py
src/commands/base.py
src/commands/compare.py
src/commands/create.py
src/commands/export.py
src/commands/get.py
src/commands/update.py
src/dto/__init__.py
src/dto/config.py
src/dto/scan_result.py
src/enums/__init__.py
src/enums/apply.py
src/enums/code.py
src/enums/reset_flag.py
src/services/__init__.py
src/services/project.py
src/services/self_check.py
src/utils/__init__.py
src/utils/apply.py
src/utils/codes.py
src/utils/display.py
src/utils/file.py
src/utils/json.py
src/utils/output.py
src/utils/response.py
src/utils/yaml.py
fosslight_cli-1.0.0.dist-info/LICENSE
fosslight_cli-1.0.0.dist-info/LICENSE.txt
fosslight_cli-1.0.0.dist-info/METADATA
fosslight_cli-1.0.0.dist-info/WHEEL
fosslight_cli-1.0.0.dist-info/entry_points.txt
fosslight_cli-1.0.0.dist-info/top_level.txt
fosslight_cli-1.0.0.dist-info/RECORD
